themis_imager_readfile/__init__.py
themis_imager_readfile/_themis.py
themis_imager_readfile-1.4.1.dist-info/LICENSE
themis_imager_readfile-1.4.1.dist-info/METADATA
themis_imager_readfile-1.4.1.dist-info/WHEEL
themis_imager_readfile-1.4.1.dist-info/RECORD
